{
  "하남": [
    {
      "date": "2026-01-01",
      "target": 1076033,
      "sales": 1250100,
      "receipts": 83,
      "per_receipt": 15061,
      "staff": 4,
      "productivity": 314450
    },
    {
      "date": "2026-01-02",
      "target": 728099,
      "sales": 762910,
      "receipts": 50,
      "per_receipt": 15258,
      "staff": 3,
      "productivity": 254303
    },
    {
      "date": "2026-01-03",
      "target": 932232,
      "sales": 952420,
      "receipts": 61,
      "per_receipt": 15613,
      "staff": 3,
      "productivity": 325907
    },
    {
      "date": "2026-01-04",
      "target": 932232,
      "sales": 1025810,
      "receipts": 52,
      "per_receipt": 19727,
      "staff": 4,
      "productivity": 256453
    },
    {
      "date": "2026-01-05",
      "target": 717355,
      "sales": 1074650,
      "receipts": 78,
      "per_receipt": 13777,
      "staff": 3,
      "productivity": 360050
    },
    {
      "date": "2026-01-06",
      "target": 717355,
      "sales": 751050,
      "receipts": 57,
      "per_receipt": 13176,
      "staff": 3,
      "productivity": 250350
    },
    {
      "date": "2026-01-07",
      "target": 717355,
      "sales": 915810,
      "receipts": 74,
      "per_receipt": 12376,
      "staff": 3,
      "productivity": 305270
    },
    {
      "date": "2026-01-08",
      "target": 717355,
      "sales": 941840,
      "receipts": 71,
      "per_receipt": 13265,
      "staff": 3,
      "productivity": 313947
    },
    {
      "date": "2026-01-09",
      "target": 717355,
      "sales": 1191980,
      "receipts": 79,
      "per_receipt": 15088,
      "staff": 3,
      "productivity": 400293
    },
    {
      "date": "2026-01-10",
      "target": 932232,
      "sales": 825180,
      "receipts": 65,
      "per_receipt": 12695,
      "staff": 3,
      "productivity": 383460
    },
    {
      "date": "2026-01-11",
      "target": 932232,
      "sales": 908810,
      "receipts": 72,
      "per_receipt": 12622,
      "staff": 3,
      "productivity": 302937
    },
    {
      "date": "2026-01-12",
      "target": 717355,
      "sales": 679510,
      "receipts": 61,
      "per_receipt": 11139,
      "staff": 3,
      "productivity": 230170
    },
    {
      "date": "2026-01-13",
      "target": 717355,
      "sales": 968330,
      "receipts": 73,
      "per_receipt": 13264,
      "staff": 3,
      "productivity": 323443
    },
    {
      "date": "2026-01-14",
      "target": 717355,
      "sales": 848160,
      "receipts": 65,
      "per_receipt": 13048,
      "staff": 3,
      "productivity": 284887
    },
    {
      "date": "2026-01-15",
      "target": 717355,
      "sales": 1016020,
      "receipts": 78,
      "per_receipt": 13025,
      "staff": 3,
      "productivity": 339907
    },
    {
      "date": "2026-01-16",
      "target": 717355,
      "sales": 891830,
      "receipts": 63,
      "per_receipt": 14156,
      "staff": 3,
      "productivity": 302010
    },
    {
      "date": "2026-01-17",
      "target": 932232,
      "sales": 1073180,
      "receipts": 69,
      "per_receipt": 15553,
      "staff": 3,
      "productivity": 413827
    },
    {
      "date": "2026-01-18",
      "target": 932232,
      "sales": 853790,
      "receipts": 58,
      "per_receipt": 14720,
      "staff": 3,
      "productivity": 291197
    },
    {
      "date": "2026-01-19",
      "target": 717355,
      "sales": 880230,
      "receipts": 58,
      "per_receipt": 15176,
      "staff": 3,
      "productivity": 295210
    },
    {
      "date": "2026-01-20",
      "target": 717355,
      "sales": 899340,
      "receipts": 79,
      "per_receipt": 11384,
      "staff": 3,
      "productivity": 308513
    },
    {
      "date": "2026-01-21",
      "target": 717355,
      "sales": 978200,
      "receipts": 67,
      "per_receipt": 14600,
      "staff": 3,
      "productivity": 329667
    },
    {
      "date": "2026-01-22",
      "target": 717355,
      "sales": 1094390,
      "receipts": 74,
      "per_receipt": 14789,
      "staff": 3,
      "productivity": 367097
    },
    {
      "date": "2026-01-23",
      "target": 717355,
      "sales": 721580,
      "receipts": 64,
      "per_receipt": 11274,
      "staff": 3,
      "productivity": 242760
    },
    {
      "date": "2026-01-24",
      "target": 932232,
      "sales": 1069140,
      "receipts": 62,
      "per_receipt": 17244,
      "staff": 3,
      "productivity": 358113
    },
    {
      "date": "2026-01-25",
      "target": 932232,
      "sales": 1096680,
      "receipts": 77,
      "per_receipt": 14242,
      "staff": 3,
      "productivity": 371127
    },
    {
      "date": "2026-01-26",
      "target": 717355,
      "sales": 720970,
      "receipts": 51,
      "per_receipt": 14136,
      "staff": 3,
      "productivity": 249523
    },
    {
      "date": "2026-01-27",
      "target": 717355,
      "sales": 841370,
      "receipts": 64,
      "per_receipt": 13146,
      "staff": 3,
      "productivity": 280457
    },
    {
      "date": "2026-01-28",
      "target": 717355,
      "sales": 783860,
      "receipts": 56,
      "per_receipt": 13997,
      "staff": 3,
      "productivity": 264887
    },
    {
      "date": "2026-01-29",
      "target": 717355,
      "sales": 1048690,
      "receipts": 76,
      "per_receipt": 13798,
      "staff": 3,
      "productivity": 351363
    },
    {
      "date": "2026-01-30",
      "target": 717355,
      "sales": 969060,
      "receipts": 78,
      "per_receipt": 12423,
      "staff": 3,
      "productivity": 324253
    },
    {
      "date": "2026-01-31",
      "target": 932232,
      "sales": 1069400,
      "receipts": 70,
      "per_receipt": 15277,
      "staff": 3,
      "productivity": 356467
    }
  ],
  "가산": [
    {
      "date": "2026-01-01",
      "target": 4545455,
      "sales": 6196450,
      "receipts": 327,
      "per_receipt": 18949,
      "staff": 13,
      "productivity": 480412
    },
    {
      "date": "2026-01-02",
      "target": 4132232,
      "sales": 4144050,
      "receipts": 238,
      "per_receipt": 17411,
      "staff": 13,
      "productivity": 323536
    },
    {
      "date": "2026-01-03",
      "target": 4132232,
      "sales": 4920448,
      "receipts": 270,
      "per_receipt": 18223,
      "staff": 15,
      "productivity": 333945
    },
    {
      "date": "2026-01-04",
      "target": 4958677,
      "sales": 6109110,
      "receipts": 344,
      "per_receipt": 17759,
      "staff": 13,
      "productivity": 474662
    },
    {
      "date": "2026-01-05",
      "target": 2892562,
      "sales": 3740620,
      "receipts": 218,
      "per_receipt": 17158,
      "staff": 15,
      "productivity": 256495
    },
    {
      "date": "2026-01-06",
      "target": 3305785,
      "sales": 3626936,
      "receipts": 210,
      "per_receipt": 17271,
      "staff": 13,
      "productivity": 282242
    },
    {
      "date": "2026-01-07",
      "target": 3719008,
      "sales": 3541210,
      "receipts": 205,
      "per_receipt": 17274,
      "staff": 13,
      "productivity": 278647
    },
    {
      "date": "2026-01-08",
      "target": 3966942,
      "sales": 3394060,
      "receipts": 212,
      "per_receipt": 16009,
      "staff": 13,
      "productivity": 261505
    },
    {
      "date": "2026-01-09",
      "target": 4545455,
      "sales": 5997950,
      "receipts": 304,
      "per_receipt": 19730,
      "staff": 14,
      "productivity": 428425
    },
    {
      "date": "2026-01-10",
      "target": 4958677,
      "sales": 4931110,
      "receipts": 302,
      "per_receipt": 16328,
      "staff": 13,
      "productivity": 388562
    },
    {
      "date": "2026-01-11",
      "target": 4958677,
      "sales": 5980310,
      "receipts": 335,
      "per_receipt": 17851,
      "staff": 13,
      "productivity": 463793
    },
    {
      "date": "2026-01-12",
      "target": 2892562,
      "sales": 3559390,
      "receipts": 205,
      "per_receipt": 17362,
      "staff": 13,
      "productivity": 283445
    },
    {
      "date": "2026-01-13",
      "target": 3305785,
      "sales": 3730010,
      "receipts": 241,
      "per_receipt": 15477,
      "staff": 13,
      "productivity": 286924
    },
    {
      "date": "2026-01-14",
      "target": 3719008,
      "sales": 3822590,
      "receipts": 225,
      "per_receipt": 16989,
      "staff": 14,
      "productivity": 279142
    },
    {
      "date": "2026-01-15",
      "target": 3966942,
      "sales": 4473580,
      "receipts": 233,
      "per_receipt": 19199,
      "staff": 13,
      "productivity": 347198
    },
    {
      "date": "2026-01-16",
      "target": 4545455,
      "sales": 5258268,
      "receipts": 297,
      "per_receipt": 17704,
      "staff": 14,
      "productivity": 376285
    },
    {
      "date": "2026-01-17",
      "target": 4958677,
      "sales": 5975780,
      "receipts": 339,
      "per_receipt": 17627,
      "staff": 13,
      "productivity": 460868
    },
    {
      "date": "2026-01-18",
      "target": 4958677,
      "sales": 5910310,
      "receipts": 335,
      "per_receipt": 17642,
      "staff": 13,
      "productivity": 455401
    },
    {
      "date": "2026-01-19",
      "target": 2892562,
      "sales": 5876720,
      "receipts": 204,
      "per_receipt": 28807,
      "staff": 13,
      "productivity": 455109
    },
    {
      "date": "2026-01-20",
      "target": 3305785,
      "sales": 3026700,
      "receipts": 176,
      "per_receipt": 17197,
      "staff": 14,
      "productivity": 216193
    },
    {
      "date": "2026-01-21",
      "target": 3719008,
      "sales": 3260260,
      "receipts": 213,
      "per_receipt": 15306,
      "staff": 13,
      "productivity": 250789
    },
    {
      "date": "2026-01-22",
      "target": 3966942,
      "sales": 3285378,
      "receipts": 195,
      "per_receipt": 16848,
      "staff": 14,
      "productivity": 238590
    },
    {
      "date": "2026-01-23",
      "target": 4545455,
      "sales": 4520558,
      "receipts": 271,
      "per_receipt": 16681,
      "staff": 14,
      "productivity": 333531
    },
    {
      "date": "2026-01-24",
      "target": 4958677,
      "sales": 5107620,
      "receipts": 286,
      "per_receipt": 17858,
      "staff": 13,
      "productivity": 395709
    },
    {
      "date": "2026-01-25",
      "target": 4958677,
      "sales": 5901902,
      "receipts": 332,
      "per_receipt": 17776,
      "staff": 13,
      "productivity": 455015
    },
    {
      "date": "2026-01-26",
      "target": 2892562,
      "sales": 2773141,
      "receipts": 182,
      "per_receipt": 15237,
      "staff": 12,
      "productivity": 232352
    },
    {
      "date": "2026-01-27",
      "target": 3305785,
      "sales": 3781498,
      "receipts": 214,
      "per_receipt": 17670,
      "staff": 11,
      "productivity": 346094
    },
    {
      "date": "2026-01-28",
      "target": 3719008,
      "sales": 4606960,
      "receipts": 227,
      "per_receipt": 20294,
      "staff": 12,
      "productivity": 384397
    },
    {
      "date": "2026-01-29",
      "target": 3966942,
      "sales": 4035380,
      "receipts": 241,
      "per_receipt": 16744,
      "staff": 13,
      "productivity": 310414
    },
    {
      "date": "2026-01-30",
      "target": 4545455,
      "sales": 4921718,
      "receipts": 266,
      "per_receipt": 18502,
      "staff": 13,
      "productivity": 381114
    },
    {
      "date": "2026-01-31",
      "target": 4958677,
      "sales": 5051100,
      "receipts": 287,
      "per_receipt": 17599,
      "staff": 15,
      "productivity": 342180
    }
  ],
  "다산": [
    {
      "date": "2026-01-01",
      "target": 14876033,
      "sales": 18112370,
      "receipts": 881,
      "per_receipt": 20558,
      "staff": 22,
      "productivity": 834111
    },
    {
      "date": "2026-01-02",
      "target": 10728099,
      "sales": 9272380,
      "receipts": 509,
      "per_receipt": 18216,
      "staff": 20,
      "productivity": 467787
    },
    {
      "date": "2026-01-03",
      "target": 13223141,
      "sales": 13762238,
      "receipts": 708,
      "per_receipt": 19438,
      "staff": 22,
      "productivity": 627632
    },
    {
      "date": "2026-01-04",
      "target": 13223141,
      "sales": 13490310,
      "receipts": 692,
      "per_receipt": 19494,
      "staff": 21,
      "productivity": 647243
    },
    {
      "date": "2026-01-05",
      "target": 6611570,
      "sales": 6502110,
      "receipts": 368,
      "per_receipt": 17668,
      "staff": 17,
      "productivity": 383995
    },
    {
      "date": "2026-01-06",
      "target": 6611570,
      "sales": 6516418,
      "receipts": 370,
      "per_receipt": 17611,
      "staff": 16,
      "productivity": 414306
    },
    {
      "date": "2026-01-07",
      "target": 6611570,
      "sales": 6806548,
      "receipts": 411,
      "per_receipt": 16560,
      "staff": 16,
      "productivity": 429421
    },
    {
      "date": "2026-01-08",
      "target": 6611570,
      "sales": 7357474,
      "receipts": 416,
      "per_receipt": 17686,
      "staff": 17,
      "productivity": 440810
    },
    {
      "date": "2026-01-09",
      "target": 7438016,
      "sales": 6570666,
      "receipts": 390,
      "per_receipt": 16847,
      "staff": 18,
      "productivity": 368034
    },
    {
      "date": "2026-01-10",
      "target": 13223141,
      "sales": 13660170,
      "receipts": 654,
      "per_receipt": 20887,
      "staff": 24,
      "productivity": 577045
    },
    {
      "date": "2026-01-11",
      "target": 13223141,
      "sales": 13834822,
      "receipts": 729,
      "per_receipt": 18977,
      "staff": 22,
      "productivity": 636419
    },
    {
      "date": "2026-01-12",
      "target": 6611570,
      "sales": 5377817,
      "receipts": 341,
      "per_receipt": 15770,
      "staff": 17,
      "productivity": 320731
    },
    {
      "date": "2026-01-13",
      "target": 6611570,
      "sales": 5655140,
      "receipts": 343,
      "per_receipt": 16487,
      "staff": 16,
      "productivity": 355071
    },
    {
      "date": "2026-01-14",
      "target": 6611570,
      "sales": 6354390,
      "receipts": 366,
      "per_receipt": 17361,
      "staff": 18,
      "productivity": 358020
    },
    {
      "date": "2026-01-15",
      "target": 6611570,
      "sales": 6779750,
      "receipts": 394,
      "per_receipt": 17207,
      "staff": 16,
      "productivity": 426531
    },
    {
      "date": "2026-01-16",
      "target": 7438016,
      "sales": 6564630,
      "receipts": 416,
      "per_receipt": 15780,
      "staff": 16,
      "productivity": 413089
    },
    {
      "date": "2026-01-17",
      "target": 13223141,
      "sales": 13432342,
      "receipts": 677,
      "per_receipt": 19840,
      "staff": 21,
      "productivity": 651850
    },
    {
      "date": "2026-01-18",
      "target": 13223141,
      "sales": 12726130,
      "receipts": 635,
      "per_receipt": 20041,
      "staff": 21,
      "productivity": 612811
    },
    {
      "date": "2026-01-19",
      "target": 6611570,
      "sales": 5729220,
      "receipts": 344,
      "per_receipt": 16654,
      "staff": 18,
      "productivity": 320151
    },
    {
      "date": "2026-01-20",
      "target": 6611570,
      "sales": 6083200,
      "receipts": 347,
      "per_receipt": 17530,
      "staff": 16,
      "productivity": 382706
    },
    {
      "date": "2026-01-21",
      "target": 6611570,
      "sales": 5908740,
      "receipts": 370,
      "per_receipt": 15969,
      "staff": 17,
      "productivity": 352885
    },
    {
      "date": "2026-01-22",
      "target": 6611570,
      "sales": 6414400,
      "receipts": 400,
      "per_receipt": 16036,
      "staff": 20,
      "productivity": 324340
    },
    {
      "date": "2026-01-23",
      "target": 7438016,
      "sales": 6040120,
      "receipts": 368,
      "per_receipt": 16413,
      "staff": 20,
      "productivity": 304821
    },
    {
      "date": "2026-01-24",
      "target": 13223141,
      "sales": 13106450,
      "receipts": 705,
      "per_receipt": 18590,
      "staff": 19,
      "productivity": 697581
    },
    {
      "date": "2026-01-25",
      "target": 13223141,
      "sales": 13801604,
      "receipts": 695,
      "per_receipt": 19858,
      "staff": 20,
      "productivity": 697418
    },
    {
      "date": "2026-01-26",
      "target": 6611570,
      "sales": 6293094,
      "receipts": 383,
      "per_receipt": 16431,
      "staff": 18,
      "productivity": 351892
    },
    {
      "date": "2026-01-27",
      "target": 6611570,
      "sales": 6169130,
      "receipts": 360,
      "per_receipt": 17136,
      "staff": 17,
      "productivity": 373837
    },
    {
      "date": "2026-01-28",
      "target": 6611570,
      "sales": 6197154,
      "receipts": 359,
      "per_receipt": 17262,
      "staff": 17,
      "productivity": 366608
    },
    {
      "date": "2026-01-29",
      "target": 6611570,
      "sales": 6169190,
      "receipts": 385,
      "per_receipt": 16023,
      "staff": 19,
      "productivity": 328321
    },
    {
      "date": "2026-01-30",
      "target": 7438016,
      "sales": 6080228,
      "receipts": 357,
      "per_receipt": 17031,
      "staff": 18,
      "productivity": 339904
    },
    {
      "date": "2026-01-31",
      "target": 13223141,
      "sales": 13627584,
      "receipts": 662,
      "per_receipt": 20585,
      "staff": 21,
      "productivity": 654653
    }
  ],
  "수원": [
    {
      "date": "2026-01-01",
      "target": 4958677,
      "sales": 7061300,
      "receipts": 178,
      "per_receipt": 39670,
      "staff": 7,
      "productivity": 1008757
    },
    {
      "date": "2026-01-02",
      "target": 3305785,
      "sales": 4274700,
      "receipts": 164,
      "per_receipt": 26065,
      "staff": 6,
      "productivity": 712450
    },
    {
      "date": "2026-01-03",
      "target": 4958677,
      "sales": 6348700,
      "receipts": 225,
      "per_receipt": 28216,
      "staff": 7,
      "productivity": 906957
    },
    {
      "date": "2026-01-04",
      "target": 4958677,
      "sales": 5064400,
      "receipts": 394,
      "per_receipt": 12853,
      "staff": 9,
      "productivity": 562711
    },
    {
      "date": "2026-01-05",
      "target": 2066115,
      "sales": 2519400,
      "receipts": 342,
      "per_receipt": 7366,
      "staff": 8,
      "productivity": 314925
    },
    {
      "date": "2026-01-06",
      "target": 2314050,
      "sales": 2729500,
      "receipts": 154,
      "per_receipt": 17724,
      "staff": 6,
      "productivity": 454916
    },
    {
      "date": "2026-01-07",
      "target": 2479339,
      "sales": 3052000,
      "receipts": 162,
      "per_receipt": 18839,
      "staff": 7,
      "productivity": 436000
    },
    {
      "date": "2026-01-08",
      "target": 2479339,
      "sales": 3134000,
      "receipts": 176,
      "per_receipt": 17806,
      "staff": 7,
      "productivity": 447714
    },
    {
      "date": "2026-01-09",
      "target": 2066115,
      "sales": 2850000,
      "receipts": 217,
      "per_receipt": 13133,
      "staff": 6,
      "productivity": 475000
    },
    {
      "date": "2026-01-10",
      "target": 4958677,
      "sales": 6552400,
      "receipts": 241,
      "per_receipt": 27188,
      "staff": 7,
      "productivity": 936057
    },
    {
      "date": "2026-01-11",
      "target": 4958677,
      "sales": 6708000,
      "receipts": 382,
      "per_receipt": 17560,
      "staff": 9,
      "productivity": 745333
    },
    {
      "date": "2026-01-12",
      "target": 2066115,
      "sales": 2620800,
      "receipts": 340,
      "per_receipt": 7708,
      "staff": 9,
      "productivity": 291200
    },
    {
      "date": "2026-01-13",
      "target": 2479339,
      "sales": 3127600,
      "receipts": 153,
      "per_receipt": 20441,
      "staff": 7,
      "productivity": 446800
    },
    {
      "date": "2026-01-14",
      "target": 2479339,
      "sales": 3078200,
      "receipts": 170,
      "per_receipt": 18107,
      "staff": 7,
      "productivity": 439742
    },
    {
      "date": "2026-01-15",
      "target": 2479339,
      "sales": 3229200,
      "receipts": 159,
      "per_receipt": 20309,
      "staff": 7,
      "productivity": 461314
    },
    {
      "date": "2026-01-16",
      "target": 2479339,
      "sales": 2970000,
      "receipts": 231,
      "per_receipt": 12857,
      "staff": 6,
      "productivity": 495000
    },
    {
      "date": "2026-01-17",
      "target": 4958677,
      "sales": 6939000,
      "receipts": 478,
      "per_receipt": 14516,
      "staff": 8,
      "productivity": 867375
    },
    {
      "date": "2026-01-18",
      "target": 4958677,
      "sales": 5893000,
      "receipts": 418,
      "per_receipt": 14098,
      "staff": 8,
      "productivity": 736625
    },
    {
      "date": "2026-01-19",
      "target": 2479339,
      "sales": 3196950,
      "receipts": 240,
      "per_receipt": 13320,
      "staff": 7,
      "productivity": 456707
    },
    {
      "date": "2026-01-20",
      "target": 2479339,
      "sales": 2960000,
      "receipts": 218,
      "per_receipt": 13577,
      "staff": 6,
      "productivity": 493333
    },
    {
      "date": "2026-01-21",
      "target": 2479339,
      "sales": 3478700,
      "receipts": 244,
      "per_receipt": 14256,
      "staff": 7,
      "productivity": 496957
    },
    {
      "date": "2026-01-22",
      "target": 2479339,
      "sales": 3341200,
      "receipts": 244,
      "per_receipt": 13693,
      "staff": 6,
      "productivity": 556866
    },
    {
      "date": "2026-01-23",
      "target": 2479339,
      "sales": 3862100,
      "receipts": 270,
      "per_receipt": 14304,
      "staff": 7,
      "productivity": 551728
    },
    {
      "date": "2026-01-24",
      "target": 4958677,
      "sales": 6906200,
      "receipts": 465,
      "per_receipt": 14852,
      "staff": 9,
      "productivity": 767355
    },
    {
      "date": "2026-01-25",
      "target": 4958677,
      "sales": 6720000,
      "receipts": 461,
      "per_receipt": 14577,
      "staff": 9,
      "productivity": 746666
    },
    {
      "date": "2026-01-26",
      "target": 2066115,
      "sales": 2977700,
      "receipts": 205,
      "per_receipt": 14525,
      "staff": 7,
      "productivity": 425385
    },
    {
      "date": "2026-01-27",
      "target": 2479339,
      "sales": 3070900,
      "receipts": 216,
      "per_receipt": 14217,
      "staff": 7,
      "productivity": 438700
    },
    {
      "date": "2026-01-28",
      "target": 2479339,
      "sales": 3173800,
      "receipts": 208,
      "per_receipt": 15258,
      "staff": 6,
      "productivity": 528966
    },
    {
      "date": "2026-01-29",
      "target": 2479339,
      "sales": 3029900,
      "receipts": 223,
      "per_receipt": 13586,
      "staff": 6,
      "productivity": 504983
    },
    {
      "date": "2026-01-30",
      "target": 2479339,
      "sales": 3508300,
      "receipts": 253,
      "per_receipt": 13866,
      "staff": 6,
      "productivity": 584716
    },
    {
      "date": "2026-01-31",
      "target": 5013223,
      "sales": 6874530,
      "receipts": 475,
      "per_receipt": 14472,
      "staff": 9,
      "productivity": 763836
    }
  ],
  "광주": [
    {
      "date": "2026-01-01",
      "target": 4132232,
      "sales": 3828210,
      "receipts": 163,
      "per_receipt": 23485,
      "staff": 13,
      "productivity": 296355
    },
    {
      "date": "2026-01-02",
      "target": 2066115,
      "sales": 1682770,
      "receipts": 81,
      "per_receipt": 20775,
      "staff": 12,
      "productivity": 140231
    },
    {
      "date": "2026-01-03",
      "target": 3305785,
      "sales": 2973540,
      "receipts": 137,
      "per_receipt": 21704,
      "staff": 12,
      "productivity": 249320
    },
    {
      "date": "2026-01-04",
      "target": 4132232,
      "sales": 3454980,
      "receipts": 150,
      "per_receipt": 23033,
      "staff": 12,
      "productivity": 291532
    },
    {
      "date": "2026-01-05",
      "target": 1652893,
      "sales": 945450,
      "receipts": 63,
      "per_receipt": 15007,
      "staff": 12,
      "productivity": 80354
    },
    {
      "date": "2026-01-06",
      "target": 1652893,
      "sales": 970400,
      "receipts": 83,
      "per_receipt": 11691,
      "staff": 12,
      "productivity": 82678
    },
    {
      "date": "2026-01-07",
      "target": 1652893,
      "sales": 1355690,
      "receipts": 83,
      "per_receipt": 16333,
      "staff": 12,
      "productivity": 115474
    },
    {
      "date": "2026-01-08",
      "target": 1652893,
      "sales": 1391940,
      "receipts": 75,
      "per_receipt": 18559,
      "staff": 10,
      "productivity": 141044
    },
    {
      "date": "2026-01-09",
      "target": 2066115,
      "sales": 1754990,
      "receipts": 97,
      "per_receipt": 18092,
      "staff": 11,
      "productivity": 270454
    },
    {
      "date": "2026-01-10",
      "target": 3305785,
      "sales": 2855160,
      "receipts": 120,
      "per_receipt": 23793,
      "staff": 12,
      "productivity": 240430
    },
    {
      "date": "2026-01-11",
      "target": 4132232,
      "sales": 2844440,
      "receipts": 142,
      "per_receipt": 20031,
      "staff": 12,
      "productivity": 241053
    },
    {
      "date": "2026-01-12",
      "target": 1652893,
      "sales": 1321290,
      "receipts": 75,
      "per_receipt": 17617,
      "staff": 12,
      "productivity": 110108
    },
    {
      "date": "2026-01-13",
      "target": 1652893,
      "sales": 1295290,
      "receipts": 82,
      "per_receipt": 15796,
      "staff": 12,
      "productivity": 107941
    },
    {
      "date": "2026-01-14",
      "target": 1652893,
      "sales": 1254000,
      "receipts": 66,
      "per_receipt": 19000,
      "staff": 12,
      "productivity": 104500
    },
    {
      "date": "2026-01-15",
      "target": 1652893,
      "sales": 2194210,
      "receipts": 106,
      "per_receipt": 20700,
      "staff": 11,
      "productivity": 199755
    },
    {
      "date": "2026-01-16",
      "target": 2066115,
      "sales": 1919570,
      "receipts": 115,
      "per_receipt": 16691,
      "staff": 12,
      "productivity": 162014
    },
    {
      "date": "2026-01-17",
      "target": 3305785,
      "sales": 3383320,
      "receipts": 168,
      "per_receipt": 20138,
      "staff": 12,
      "productivity": 284443
    },
    {
      "date": "2026-01-18",
      "target": 4132232,
      "sales": 1293100,
      "receipts": 61,
      "per_receipt": 21198,
      "staff": 12,
      "productivity": 107758
    },
    {
      "date": "2026-01-19",
      "target": 1652893,
      "sales": 194950,
      "receipts": null,
      "per_receipt": null,
      "staff": 11,
      "productivity": 17723
    },
    {
      "date": "2026-01-20",
      "target": 1652893,
      "sales": 946870,
      "receipts": 64,
      "per_receipt": 14795,
      "staff": 11,
      "productivity": 86079
    },
    {
      "date": "2026-01-21",
      "target": 1652893,
      "sales": 1520380,
      "receipts": 84,
      "per_receipt": 18100,
      "staff": 11,
      "productivity": 138216
    },
    {
      "date": "2026-01-22",
      "target": 1652893,
      "sales": 1626780,
      "receipts": 94,
      "per_receipt": 17306,
      "staff": 13,
      "productivity": 125137
    },
    {
      "date": "2026-01-23",
      "target": 2066115,
      "sales": 1388200,
      "receipts": 80,
      "per_receipt": 17353,
      "staff": 11,
      "productivity": 126200
    },
    {
      "date": "2026-01-24",
      "target": 3305785,
      "sales": 3704770,
      "receipts": 176,
      "per_receipt": 21049,
      "staff": 12,
      "productivity": 310331
    },
    {
      "date": "2026-01-25",
      "target": 4132232,
      "sales": 4081790,
      "receipts": 180,
      "per_receipt": 22677,
      "staff": 10,
      "productivity": 408179
    },
    {
      "date": "2026-01-26",
      "target": 1652893,
      "sales": 982370,
      "receipts": 73,
      "per_receipt": 13457,
      "staff": 10,
      "productivity": 100277
    },
    {
      "date": "2026-01-27",
      "target": 1652893,
      "sales": 999950,
      "receipts": 66,
      "per_receipt": 15150,
      "staff": 10,
      "productivity": 102425
    },
    {
      "date": "2026-01-28",
      "target": 1652893,
      "sales": 1839920,
      "receipts": 110,
      "per_receipt": 16727,
      "staff": 12,
      "productivity": 153327
    },
    {
      "date": "2026-01-29",
      "target": 1652893,
      "sales": 1124320,
      "receipts": 84,
      "per_receipt": 13385,
      "staff": 12,
      "productivity": 93693
    },
    {
      "date": "2026-01-30",
      "target": 2066115,
      "sales": 1320020,
      "receipts": 76,
      "per_receipt": 17369,
      "staff": 11,
      "productivity": 120002
    },
    {
      "date": "2026-01-31",
      "target": 3305785,
      "sales": 4613340,
      "receipts": 219,
      "per_receipt": 21065,
      "staff": 12,
      "productivity": 384445
    }
  ],
  "운정": [
    {
      "date": "2026-01-01",
      "target": 8264463,
      "sales": 12015545,
      "receipts": 825,
      "per_receipt": 14564,
      "staff": 17,
      "productivity": 706797
    },
    {
      "date": "2026-01-02",
      "target": 5702479,
      "sales": 8784818,
      "receipts": 649,
      "per_receipt": 13536,
      "staff": 17,
      "productivity": 516754
    },
    {
      "date": "2026-01-03",
      "target": 8264463,
      "sales": 10284909,
      "receipts": 716,
      "per_receipt": 14364,
      "staff": 17,
      "productivity": 604995
    },
    {
      "date": "2026-01-04",
      "target": 8264463,
      "sales": 9593727,
      "receipts": 694,
      "per_receipt": 13824,
      "staff": 16,
      "productivity": 599608
    },
    {
      "date": "2026-01-05",
      "target": 5619835,
      "sales": 5258364,
      "receipts": 389,
      "per_receipt": 13518,
      "staff": 14,
      "productivity": 375597
    },
    {
      "date": "2026-01-06",
      "target": 5619835,
      "sales": 5457000,
      "receipts": 404,
      "per_receipt": 13507,
      "staff": 14,
      "productivity": 389786
    },
    {
      "date": "2026-01-07",
      "target": 5785124,
      "sales": 5287545,
      "receipts": 403,
      "per_receipt": 13120,
      "staff": 14,
      "productivity": 377682
    },
    {
      "date": "2026-01-08",
      "target": 5785124,
      "sales": 6124636,
      "receipts": 449,
      "per_receipt": 13641,
      "staff": 15,
      "productivity": 408309
    },
    {
      "date": "2026-01-09",
      "target": 5785124,
      "sales": 6524273,
      "receipts": 494,
      "per_receipt": 13207,
      "staff": 16,
      "productivity": 407767
    },
    {
      "date": "2026-01-10",
      "target": 8264463,
      "sales": 9253455,
      "receipts": 719,
      "per_receipt": 12870,
      "staff": 16,
      "productivity": 578341
    },
    {
      "date": "2026-01-11",
      "target": 8264463,
      "sales": 9626455,
      "receipts": 656,
      "per_receipt": 14674,
      "staff": 17,
      "productivity": 566262
    },
    {
      "date": "2026-01-12",
      "target": 5619835,
      "sales": 5249909,
      "receipts": 372,
      "per_receipt": 14113,
      "staff": 15,
      "productivity": 349994
    },
    {
      "date": "2026-01-13",
      "target": 5619835,
      "sales": 5834909,
      "receipts": 346,
      "per_receipt": 16864,
      "staff": 13,
      "productivity": 448839
    },
    {
      "date": "2026-01-14",
      "target": 5619835,
      "sales": 5885545,
      "receipts": 374,
      "per_receipt": 15737,
      "staff": 14,
      "productivity": 420396
    },
    {
      "date": "2026-01-15",
      "target": 5619835,
      "sales": 5434455,
      "receipts": 330,
      "per_receipt": 16468,
      "staff": 13,
      "productivity": 418035
    },
    {
      "date": "2026-01-16",
      "target": 5619835,
      "sales": 6644273,
      "receipts": 375,
      "per_receipt": 17718,
      "staff": 14,
      "productivity": 474591
    },
    {
      "date": "2026-01-17",
      "target": 8264463,
      "sales": 9951636,
      "receipts": 570,
      "per_receipt": 17459,
      "staff": 16,
      "productivity": 621977
    },
    {
      "date": "2026-01-18",
      "target": 8264463,
      "sales": 8691091,
      "receipts": 478,
      "per_receipt": 18182,
      "staff": 16,
      "productivity": 543193
    },
    {
      "date": "2026-01-19",
      "target": 5619835,
      "sales": 5624909,
      "receipts": 326,
      "per_receipt": 17254,
      "staff": 13,
      "productivity": 432685
    },
    {
      "date": "2026-01-20",
      "target": 5619835,
      "sales": 5144000,
      "receipts": 373,
      "per_receipt": 13791,
      "staff": 13,
      "productivity": 395692
    },
    {
      "date": "2026-01-21",
      "target": 5619835,
      "sales": 5279727,
      "receipts": 402,
      "per_receipt": 13134,
      "staff": 14,
      "productivity": 377123
    },
    {
      "date": "2026-01-22",
      "target": 5619835,
      "sales": 3994455,
      "receipts": 299,
      "per_receipt": 13359,
      "staff": 14,
      "productivity": 285318
    },
    {
      "date": "2026-01-23",
      "target": 5619835,
      "sales": 4490273,
      "receipts": 330,
      "per_receipt": 13607,
      "staff": 13,
      "productivity": 345406
    },
    {
      "date": "2026-01-24",
      "target": 8264463,
      "sales": 7863364,
      "receipts": 550,
      "per_receipt": 14297,
      "staff": 16,
      "productivity": 491460
    },
    {
      "date": "2026-01-25",
      "target": 8264463,
      "sales": 7714273,
      "receipts": 549,
      "per_receipt": 14051,
      "staff": 15,
      "productivity": 514285
    },
    {
      "date": "2026-01-26",
      "target": 5702479,
      "sales": 4551727,
      "receipts": 334,
      "per_receipt": 13628,
      "staff": 15,
      "productivity": 303448
    },
    {
      "date": "2026-01-27",
      "target": 5619835,
      "sales": 4003273,
      "receipts": 295,
      "per_receipt": 13570,
      "staff": 13,
      "productivity": 307944
    },
    {
      "date": "2026-01-28",
      "target": 5619835,
      "sales": 4607182,
      "receipts": 339,
      "per_receipt": 13591,
      "staff": 14,
      "productivity": 329084
    },
    {
      "date": "2026-01-29",
      "target": 5619835,
      "sales": 4448727,
      "receipts": 331,
      "per_receipt": 13440,
      "staff": 13,
      "productivity": 342210
    },
    {
      "date": "2026-01-30",
      "target": 5647934,
      "sales": 4871545,
      "receipts": 370,
      "per_receipt": 13166,
      "staff": 13,
      "productivity": 374734
    },
    {
      "date": "2026-01-31",
      "target": 8264463,
      "sales": 8071818,
      "receipts": 586,
      "per_receipt": 13774,
      "staff": 17,
      "productivity": 474813
    }
  ]
}